entanglekey/__init__.py
entanglekey/cli.py
entanglekey/config.py
entanglekey/config_loader.py
entanglekey/core.py
entanglekey/crypto.py
entanglekey/exceptions.py
entanglekey/logging_config.py
entanglekey/network.py
entanglekey/quantum.py
entanglekey/security_monitor.py
entanglekey-1.0.0.dist-info/licenses/LICENSE
tests/__init__.py
tests/test_basic.py
tests/test_integration.py
entanglekey-1.0.0.dist-info/METADATA
entanglekey-1.0.0.dist-info/WHEEL
entanglekey-1.0.0.dist-info/entry_points.txt
entanglekey-1.0.0.dist-info/top_level.txt
entanglekey-1.0.0.dist-info/RECORD
